cdmc/__init__.py
cdmc/cal.py
cdmc/console.py
cdmc-0.1.1.dist-info/DESCRIPTION.rst
cdmc-0.1.1.dist-info/METADATA
cdmc-0.1.1.dist-info/RECORD
cdmc-0.1.1.dist-info/WHEEL
cdmc-0.1.1.dist-info/entry_points.txt
cdmc-0.1.1.dist-info/metadata.json
cdmc-0.1.1.dist-info/top_level.txt
