Metadata-Version: 2.0
Name: cdmc
Version: 0.1.1
Summary: Tools for using the Cinco De Mayo Calendar
Home-page: https://github.com/MineRobber9000/cdmc
Author: Robert Miles
Author-email: milesrobert374@gmail.com
License: MIT
Keywords: novelty-calendars
Platform: UNKNOWN
Classifier: Development Status :: 4 - Beta
Classifier: License :: OSI Approved :: MIT License
Classifier: Programming Language :: Python :: 2
Classifier: Programming Language :: Python :: 2.7
